setup.cfg
setup.py
simplyrets/PropertiesApi.py
simplyrets/__init__.py
simplyrets/example.py
simplyrets/simplyrets.py
simplyrets.egg-info/PKG-INFO
simplyrets.egg-info/SOURCES.txt
simplyrets.egg-info/dependency_links.txt
simplyrets.egg-info/top_level.txt
simplyrets/models/Agent.py
simplyrets/models/ContactInformation.py
simplyrets/models/GeographicData.py
simplyrets/models/Listing.py
simplyrets/models/MlsInformation.py
simplyrets/models/Office.py
simplyrets/models/Property.py
simplyrets/models/School.py
simplyrets/models/StreetAddress.py
simplyrets/models/Tax.py
simplyrets/models/__init__.py