Metadata-Version: 1.1
Name: simplyrets
Version: 0.1
Summary: SimplyRETS Listings API for Python
Home-page: https://simplyrets.com
Author: Christopher Reichert
Author-email: christopher@simplyrets.com
License: MIT
Download-URL: https://github.com/SimplyRETS/simplyrets-python-sdk/archive/v0.1.tar.gz
Keywords: simplyrets,rets api
Platform: UNKNOWN
